discrevpy/__init__.py
discrevpy/simulator.py
discrevpy-1.0.3.dist-info/LICENSE
discrevpy-1.0.3.dist-info/METADATA
discrevpy-1.0.3.dist-info/WHEEL
discrevpy-1.0.3.dist-info/top_level.txt
discrevpy-1.0.3.dist-info/RECORD
