Metadata-Version: 2.1
Name: discrevpy
Version: 1.0.3
Summary: Minimalist discrete event simulator
Home-page: https://github.com/snkas/discrevpy
Author: snkas
Author-email: snkasdev+discrevpy@gmail.com
License: MIT
Project-URL: Documentation, https://snkas.github.io/discrevpy/
Project-URL: Bug Tracker, https://github.com/snkas/discrevpy/issues
Project-URL: Source Code, https://github.com/snkas/discrevpy
Platform: UNKNOWN
Classifier: Development Status :: 4 - Beta
Classifier: Programming Language :: Python :: 3 :: Only
Classifier: License :: OSI Approved :: MIT License
Classifier: Operating System :: OS Independent
Requires-Python: >=3.7
